Workbook

Sheet 116_総括表
A1: No. | B1: 科 目 | C1: 名目額(簿価額等)(円) | D1: 回収見込額(円) | E1: 備 考
A2: 1 | B2: 現金
A3: 2 | B3: 預貯金 | F3: =IF('117 _預貯金'!B2="",1,0) -> 1
A4: 3 | B4: 受取手形・小切手 | F4: =IF('118_手形・小切手'!B2="",1,0) -> 1
A5: 4 | B5: 売掛金 | F5: =IF('119_売掛金'!B2="",1,0) -> 1
A6: 5 | B6: 在庫商品 | F6: =IF('120_在庫商品'!B2="",1,0) -> 1
A7: 6 | B7: 貸付金 | F7: =IF('121_貸付金'!B2="",1,0) -> 1
A8: 7 | B8: 不動産 | F8: =IF('122_不動産'!B2="",1,0) -> 1
A9: 8 | B9: 機械・工具類 | F9: =IF('123_機械・工具類'!B2="",1,0) -> 1
A10: 9 | B10: 什器備品 | F10: =IF('124_什器備品'!B2="",1,0) -> 1
A11: 10 | B11: 自動車 | F11: =IF('125_自動車'!B2="",1,0) -> 1
A12: 11 | B12: 有価証券 | F12: =IF(#REF!="",1,0) -> #REF!
A13: 12 | B13: 賃借保証金・敷金 | F13: =IF('126_有価証券'!B2="",1,0) -> 1
A14: 13 | B14: 保険解約返戻金 | F14: =IF('127_賃借保証金・敷金'!B2="",1,0) -> 1
A15: 14 | B15: 過払金 | F15: =IF('128_保険'!B2="",1,0) -> 1
A16: 15 | B16: その他
A17: 16 | F17: =IF('130_その他'!B2="",1,0) -> 1
A18: 合計 | C18: =SUM(C2:C17) -> 0 | D18: =SUM(D2:D17) -> 0

Sheet 117 _預貯金
A1: No. | B1: 金融機関名 | C1: 支店名 | D1: 種類 | E1: 口座番号 | F1: 残高（円） | G1: 相殺予定 | H1: 回収見込額（円） | I1: 通帳等 | J1: 備 考
A2: 1 | G2: □ | H2: =IF(F2="","",F2) | I2: □
A3: 2 | G3: □ | H3: =IF(F3="","",F3) | I3: □
A4: 3 | G4: □ | H4: =IF(F4="","",F4) | I4: □
A5: 4 | G5: □ | H5: =IF(F5="","",F5) | I5: □
A6: 5 | G6: □ | H6: =IF(F6="","",F6) | I6: □
A7: 6 | G7: □ | H7: =IF(F7="","",F7) | I7: □
A8: 7 | G8: □ | H8: =IF(F8="","",F8) | I8: □
A9: 8 | G9: □ | H9: =IF(F9="","",F9) | I9: □
A10: 9 | G10: □ | H10: =IF(F10="","",F10) | I10: □
A11: 10 | G11: □ | H11: =IF(F11="","",F11) | I11: □
A12: 11 | G12: □ | H12: =IF(F12="","",F12) | I12: □
A13: 12 | G13: □ | H13: =IF(F13="","",F13) | I13: □
E14: 合計 | F14: =SUM(F2:F13) -> 0 | H14: =SUM(H2:H13) -> 0

Sheet 118_手形・小切手
A1: No. | B1: 振出人の氏名又は会社名 | C1: 〒 | D1: 住 所 | E1: ＴＥＬ ＦＡＸ | F1: 手形小切手番号 | G1: 裏書人 | H1: 支払期日 | I1: 額面（円） | J1: 回収見込額（円） | K1: 備考
A2: 1
A3: 2
A4: 3
A5: 4
A6: 5
A7: 6
A8: 7
A9: 8
A10: 9
A11: 10
A12: 11
A13: 12
... A21: 20
H22: 合計 | I22: =SUM(I2:I21) -> 0 | J22: =SUM(J2:J21) -> 0

Sheet 119_売掛金
A1: No. | B1: 債務者の氏名又は会社名 | C1: 〒 | D1: 住 所 | E1: ＴＥＬ ＦＡＸ | F1: 金 額（円） | G1: 回収見込額（円） | H1: 契約書等 | I1: 備考
A2: 1 | H2: □
A3: 2 | H3: □
A4: 3 | H4: □
A5: 4 | H5: □
A6: 5 | H6: □
A7: 6 | H7: □
A8: 7 | H8: □
A9: 8 | H9: □
A10: 9 | H10: □
A11: 10 | H11: □
A12: 11 | H12: □
A13: 12 | H13: □
... A21: 20 | H21: □
E22: 合計 | F22: =SUM(F2:F21) -> 0 | G22: =SUM(G2:G21) -> 0

Sheet 120_在庫商品
A1: No. | B1: 品名 | C1: 個数 | D1: 所在場所 | E1: 簿価等（円） | F1: 回収見込額（円） | G1: 備考
A2: 1
A3: 2
A4: 3
A5: 4
A6: 5
A7: 6
A8: 7
A9: 8
A10: 9
A11: 10
A12: 11
A13: 12
D14: 合計 | E14: =SUM(E2:E13) -> 0 | F14: =SUM(F2:F13) -> 0

Sheet 121_貸付金
A1: No. | B1: 債務者の氏名又は会社名 | C1: 〒 | D1: 住 所 | E1: ＴＥＬ ＦＡＸ | F1: 金 額（円） | G1: 回収見込額（円） | H1: 契約書等 | I1: 備考
A2: 1 | H2: □
A3: 2 | H3: □
A4: 3 | H4: □
A5: 4 | H5: □
A6: 5 | H6: □
A7: 6 | H7: □
A8: 7 | H8: □
A9: 8 | H9: □
A10: 9 | H10: □
A11: 10 | H11: □
A12: 11 | H12: □
A13: 12 | H13: □
... A21: 20 | H21: □
E22: 合計 | F22: =SUM(F2:F21) -> 0 | G22: =SUM(G2:G21) -> 0

Sheet 122_不動産
A1: No. | B1: 種類 | C1: 所在地 | D1: 地番又は家屋番号 | E1: 評価額(固定資産評価証明書) 又は 査定価格(査定書) （円） | F1: 被担保債権額 （円） | G1: 回収見込額（円） | H1: 評価証明書等 | I1: 査定書 | J1: 被担保債権 残額証明書 | K1: 備 考
A2: 1 | H2: □ | I2: □ | J2: □
A3: 2 | H3: □ | I3: □ | J3: □
A4: 3 | H4: □ | I4: □ | J4: □
A5: 4 | H5: □ | I5: □ | J5: □
A6: 5 | H6: □ | I6: □ | J6: □
A7: 6 | H7: □ | I7: □ | J7: □
A8: 7 | H8: □ | I8: □ | J8: □
A9: 8 | H9: □ | I9: □ | J9: □
A10: 9 | H10: □ | I10: □ | J10: □
A11: 10 | H11: □ | I11: □ | J11: □
D12: 合計 | E12: =SUM(E2:E11) -> 0 | F12: =SUM(F2:F11) -> 0 | G12: =SUM(G2:G11) -> 0

Sheet 123_機械・工具類
A1: No. | B1: 名称 | C1: 個数 | D1: 所在場所 | E1: 簿価等（円） | F1: 回収見込額（円） | G1: 備 考
A2: 1
A3: 2
A4: 3
A5: 4
A6: 5
A7: 6
A8: 7
A9: 8
A10: 9
A11: 10
A12: 11
A13: 12
D14: 合計 | E14: =SUM(E2:E13) -> 0 | F14: =SUM(F2:F13) -> 0

Sheet 124_什器備品
A1: No. | B1: 品名 | C1: 個数 | D1: 所在場所 | E1: 簿価等（円） | F1: 回収見込額（円） | G1: 備 考
A2: 1
A3: 2
A4: 3
A5: 4
A6: 5
A7: 6
A8: 7
A9: 8
A10: 9
A11: 10
A12: 11
A13: 12
D14: 合計 | E14: =SUM(E2:E13) -> 0 | F14: =SUM(F2:F13) -> 0

Sheet 125_自動車
A1: No. | B1: 車名 | C1: 初度登録年 | D1: 登録番号 | E1: 保管場所 | F1: 簿価等（円） | G1: 回収見込額（円） | H1: 所有権留保 | I1: 登録事項証明書等 | J1: 備考
A2: 1 | H2: □ | I2: □
A3: 2 | H3: □ | I3: □
A4: 3 | H4: □ | I4: □
A5: 4 | H5: □ | I5: □
A6: 5 | H6: □ | I6: □
A7: 6 | H7: □ | I7: □
A8: 7 | H8: □ | I8: □
A9: 8 | H9: □ | I9: □
A10: 9 | H10: □ | I10: □
A11: 10 | H11: □ | I11: □
E12: 合計 | F12: =SUM(F2:F11) -> 0 | G12: =SUM(G2:G11) -> 0

Sheet 126_有価証券
A1: No. | B1: 財産の内容 （ゴルフ会員権・株式・出資金等） | C1: 数量 | D1: 証券等番号 | E1: 証券等／所在場所 | G1: 簿価等（円） | H1: 回収見込額（円） | I1: 取引相場資料 | J1: 備 考
A2: 1 | E2: □ | I2: □
A3: 2 | E3: □ | I3: □
A4: 3 | E4: □ | I4: □
A5: 4 | E5: □ | I5: □
A6: 5 | E6: □ | I6: □
A7: 6 | E7: □ | I7: □
A8: 7 | E8: □ | I8: □
A9: 8 | E9: □ | I9: □
A10: 9 | E10: □ | I10: □
A11: 10 | E11: □ | I11: □
A12: 11 | E12: □ | I12: □
A13: 12 | E13: □ | I13: □
E14: 合計 | G14: =SUM(G2:G13) -> 0 | H14: =SUM(H2:H13) -> 0

Sheet 127_賃借保証金・敷金
A1: No. | B1: 賃借物件名 | C1: 差入額（円） | D1: 契約上の返戻金（円） | E1: 滞納額（円） | F1: 原状回復費用等の見込額（円） | G1: 回収見込額（円） | H1: 契約書等 | I1: 備考
A2: 1 | D2: =C2 -> 0 | H2: □
A3: 2 | D3: =C3 -> 0 | H3: □
A4: 3 | D4: =C4 -> 0 | H4: □
A5: 4 | D5: =C5 -> 0 | H5: □
A6: 5 | D6: =C6 -> 0 | H6: □
A7: 6 | D7: =C7 -> 0 | H7: □
A8: 7 | D8: =C8 -> 0 | H8: □
A9: 8 | D9: =C9 -> 0 | H9: □
A10: 9 | D10: =C10 -> 0 | H10: □
A11: 10 | D11: =C11 -> 0 | H11: □
A12: 11 | D12: =C12 -> 0 | H12: □
A13: 12 | D13: =C13 -> 0 | H13: □
B14: 合計 | C14: =SUM(C2:C13) -> 0 | D14: =SUM(D2:D13) -> 0 | E14: =SUM(E2:E13) -> 0 | F14: =SUM(F2:F13) -> 0 | G14: =SUM(G2:G13) -> 0

Sheet 128_保険
A1: No. | B1: 保険会社名 | C1: 保険種類 | D1: 証券番号 | E1: 名目額 （解約返戻金）（円） | F1: 回収見込額 （解約返戻金）（円） | G1: 証券 | H1: 備 考
A2: 1 | G2: □
A3: 2 | G3: □
A4: 3 | G4: □
A5: 4 | G5: □
A6: 5 | G6: □
A7: 6 | G7: □
A8: 7 | G8: □
A9: 8 | G9: □
A10: 9 | G10: □
A11: 10 | G11: □
A12: 11 | G12: □
A13: 12 | G13: □
D14: 合計 | E14: =SUM(E2:E13) -> 0 | F14: =SUM(F2:F13) -> 0

Sheet 129_過払金
A1: No. | B1: 相手方の氏名又は会社名 | C1: 額面額 | D1: 合意額又は 見込み額（円） | E1: 回収費用控除 予定額（円） | F1: 回収費用控除後 残金(円） | G1: 合意又は 債務名義 取得の有無 | H1: 備考
A2: 1 | G2: □
A3: 2 | G3: □
A4: 3 | G4: □
A5: 4 | G5: □
A6: 5 | G6: □
A7: 6 | G7: □
A8: 7 | G8: □
A9: 8 | G9: □
A10: 9 | G10: □
A11: 10 | G11: □
B12: 合計 | C12: =SUM(C2:C11) -> 0 | D12: =SUM(D2:D11) -> 0 | E12: =SUM(E2:E11) -> 0 | F12: =SUM(F2:F11) -> 0

Sheet 130_その他
A1: No. | B1: 財産の種類・内容 | C1: 数量 | D1: 所在場所 | E1: 簿価等（円） | F1: 回収見込額（円） | G1: 備 考
A2: 1
A3: 2
A4: 3
A5: 4
A6: 5
A7: 6
A8: 7
A9: 8
A10: 9
A11: 10
A12: 11
A13: 12
D14: 合計 | E14: =SUM(E2:E13) -> 0 | F14: =SUM(F2:F13) -> 0

Sheet 131_処分済財産
A1: ※ | B1: ただし，①現金，②預貯金，③受取手形・小切手，④売掛金，⑤在庫商品（原材料）など，通常流動性が高いと思われる資産については記入する必要がありません。 ⑥貸付金，⑦不動産，⑧機械・工具類，⑨什器備品，⑩自動車，⑪有価証券，⑫賃借保証金・敷金，⑬保険解約返戻金，⑮その他の財産等の資産についてのみ記入してください。
A2: No. | B2: 財産の種類・内容 | C2: 架空計上 | D2: 処分 | E2: 処分日 | F2: 処分価格(円） | G2: 処分代金の使途 又は 財産目録非掲載の理由
A3: 1 | C3: □ | D3: □
A4: 2 | C4: □ | D4: □
A5: 3 | C5: □ | D5: □
A6: 4 | C6: □ | D6: □
A7: 5 | C7: □ | D7: □
A8: 6 | C8: □ | D8: □
A9: 7 | C9: □ | D9: □
A10: 8 | C10: □ | D10: □
A11: 9 | C11: □ | D11: □
A12: 10 | C12: □ | D12: □
A13: 11 | C13: □ | D13: □
A14: 12 | C14: □ | D14: □
