Workbook

Sheet 218_総括表
A1: No. | B1: 科 目 | C1: 名目額(簿価額等)(円) | D1: 回収見込額(円) | E1: 備 考 | F1: 自由財産の額 及び 拡張を求める財産の額 (円)
A2: 1 | B2: 現金
A3: 2 | B3: 預貯金・積立金 | G3: =IF('219_預貯金・積立金'!F2="",1,0) -> 1
A4: 3 | B4: 保険解約返戻金 | G4: =IF('220_保険'!E2="",1,0) -> 1
A5: 4 | B5: 自動車 | G5: =IF('221_自動車'!F2="",1,0) -> 1
A6: 5 | B6: 賃借保証金・敷金 | G6: =IF('222_敷金'!C2="",1,0) -> 1
A7: 6 | B7: 退職金 | G7: =IF(#REF!="",1,0) -> #REF!
A8: 7 | B8: 過払金 | G8: =IF('223_退職金'!D2="",1,0) -> 1
A9: 8 | B9: 不動産
A10: 9 | B10: 有価証券 | G10: =IF('225_不動産'!E2="",1,0) -> 1
A11: 10 | B11: 受取手形・小切手 | G11: =IF('226_有価証券'!G2="",1,0) -> 1
A12: 11 | B12: 売掛金 | G12: =IF('227_手形・小切手'!I2="",1,0) -> 1
A13: 12 | B13: 貸付金 | G13: =IF('228_売掛金'!F2="",1,0) -> 1
A14: 13 | B14: 在庫商品 | G14: =IF('229_貸付金'!F2="",1,0) -> 1
A15: 14 | B15: 機械・工具類 | G15: =IF('230_在庫商品'!E2="",1,0) -> 1
A16: 15 | B16: 什器備品 | G16: =IF('231_機械・工具類'!E2="",1,0) -> 1
A17: 16 | B17: その他 | G17: =IF('232_什器備品'!E2="",1,0) -> 1
A18: 17 | G18: =IF('233_その他'!E5="",1,0) -> 1
A19: 合計 | C19: =SUM(C2:C18) -> 0 | D19: =SUM(D2:D18) -> 0 | F19: =SUM(F2:F18) -> 0

Sheet 219_預貯金・積立金
A1: No. | B1: 金融機関又は 積立先の名称 | C1: 支店名 | D1: 種類 | E1: 口座番号・ 積立番号等 | F1: 残高又は 積立総額（円） | G1: 相殺予定 | H1: 回収見込額（円） | I1: 通帳等 | J1: 備 考 | K1: 自由財産 拡張申立
A2: 1 | G2: □ | I2: □ | K2: □
A3: 2 | G3: □ | I3: □ | K3: □
A4: 3 | G4: □ | I4: □ | K4: □
A5: 4 | G5: □ | I5: □ | K5: □
A6: 5 | G6: □ | I6: □ | K6: □
A7: 6 | G7: □ | I7: □ | K7: □
A8: 7 | G8: □ | I8: □ | K8: □
A9: 8 | G9: □ | I9: □ | K9: □
A10: 9 | G10: □ | I10: □ | K10: □
A11: 10 | G11: □ | I11: □ | K11: □
E12: 合計 | F12: =SUM(F2:F11) -> 0 | H12: =SUM(H2:H11) -> 0 | K12: {=SUM(H2:H11*IF(K2:K11="■",1,0))} -> 0

Sheet 220_保険
A1: No. | B1: 保険会社名 | C1: 保険種類 | D1: 証券番号 | E1: 名目額 （解約返戻金）（円） | F1: 回収見込額 （解約返戻金）（円） | G1: 証券 | H1: 備 考 | I1: 自由財産 拡張申立
A2: 1 | G2: □ | I2: □
A3: 2 | G3: □ | I3: □
A4: 3 | G4: □ | I4: □
A5: 4 | G5: □ | I5: □
A6: 5 | G6: □ | I6: □
A7: 6 | G7: □ | I7: □
A8: 7 | G8: □ | I8: □
A9: 8 | G9: □ | I9: □
A10: 9 | G10: □ | I10: □
A11: 10 | G11: □ | I11: □
D12: 合計 | E12: =SUM(E2:E11) -> 0 | F12: =SUM(F2:F11) -> 0 | I12: {=SUM(F2:F11*IF(I2:I11="■",1,0))} -> 0

Sheet 221_自動車
A1: No. | B1: 車名 | C1: 初度登録年 | D1: 登録番号 | E1: 保管場所 | F1: 簿価等 （円） | G1: 回収見込額 （円） | H1: 所有権留保 | I1: 登録事項 証明書等 | J1: 備考 | K1: 自由財産 拡張申立
A2: 1 | H2: □ | I2: □ | K2: □
A3: 2 | H3: □ | I3: □ | K3: □
A4: 3 | H4: □ | I4: □ | K4: □
A5: 4 | H5: □ | I5: □ | K5: □
A6: 5 | H6: □ | I6: □ | K6: □
A7: 6 | H7: □ | I7: □ | K7: □
E8: 合計 | F8: =SUM(F2:F7) -> 0 | G8: =SUM(G2:G7) -> 0 | K8: {=SUM(G2:G7*IF(K2:K7="■",1,0))} -> 0

Sheet 222_敷金
A1: No. | B1: 賃借物件 | C1: 差入額（円） | D1: 契約上の返戻金（円） | E1: 滞納額（円） | F1: 原状回復費用等の見込額（円） | G1: 回収見込額（円） | H1: 契約 書等 | I1: 備考 | J1: 自由財産 拡張申立
A2: 1 | D2: =C2 -> 0 | H2: □ | J2: □
A3: 2 | D3: =C3 -> 0 | H3: □ | J3: □
A4: 3 | D4: =C4 -> 0 | H4: □ | J4: □
A5: 4 | D5: =C5 -> 0 | H5: □ | J5: □
B6: 合計 | C6: =SUM(C2:C5) -> 0 | D6: =SUM(D2:D5) -> 0 | E6: =SUM(E2:E5) -> 0 | F6: =SUM(F2:F5) -> 0 | G6: =SUM(G2:G5) -> 0 | J6: {=SUM(G2:G5*IF(J2:J5="■",1,0))} -> 0

Sheet 223_退職金
A1: No. | B1: 雇用主の氏名又は会社名 | C1: 勤務開始日 | D1: 支給見込額（円） | E1: 1/8相当額（円） | F1: 証明書 | G1: 退職金 規程 | H1: 備 考 | I1: 自由財産 拡張申立
A2: 1 | E2: =ROUNDUP(D2/8,0) -> 0 | F2: □ | G2: □ | I2: □
A3: 2 | E3: =ROUNDUP(D3/8,0) -> 0 | F3: □ | G3: □ | I3: □
A4: 3 | E4: =ROUNDUP(D4/8,0) -> 0 | F4: □ | G4: □ | I4: □
A5: 4 | E5: =ROUNDUP(D5/8,0) -> 0 | F5: □ | G5: □ | I5: □
C6: 合計 | D6: =SUM(D2:D5) -> 0 | E6: =SUM(E2:E5) -> 0 | I6: {=SUM(E2:E5*IF(I2:I5="■",1,0))} -> 0

Sheet 224_過払金
A1: No. | B1: 相手方の氏名 又は会社名 | C1: 額面額（円） | D1: 合意額又は 見込み額（円） | E1: 回収費用控除 予定額（円） | F1: 回収費用控除後残金（円） | G1: 合意又は 債務名義 取得 | H1: 備考 | I1: 自由財産 拡張申立
A2: 1 | G2: □ | I2: □
A3: 2 | G3: □ | I3: □
A4: 3 | G4: □ | I4: □
A5: 4 | G5: □ | I5: □
A6: 5 | G6: □ | I6: □
A7: 6 | G7: □ | I7: □
A8: 7 | G8: □ | I8: □
A9: 8 | G9: □ | I9: □
A10: 9 | G10: □ | I10: □
A11: 10 | G11: □ | I11: □
B12: 合計 | C12: =SUM(C2:C11) -> 0 | D12: =SUM(D2:D11) -> 0 | E12: =SUM(E2:E11) -> 0 | F12: =SUM(F2:F11) -> 0 | I12: {=SUM(F2:F11*IF(I2:I11="■",1,0))} -> 0

Sheet 225_不動産
A1: No. | B1: 種類 | C1: 所在地 | D1: 地番又は家屋番号 | E1: 評価額(固定資産評価証明書) 又は 査定価格(査定書) （円） | F1: 被担保債権額 （円） | G1: 回収見込額（円） | H1: 評価証明書等 | I1: 査定書 | J1: 被担保債権 残額証明書 | K1: 備 考 | L1: 自由財産 拡張申立
A2: 1 | H2: □ | I2: □ | J2: □ | L2: □
A3: 2 | H3: □ | I3: □ | J3: □ | L3: □
A4: 3 | H4: □ | I4: □ | J4: □ | L4: □
A5: 4 | H5: □ | I5: □ | J5: □ | L5: □
A6: 5 | H6: □ | I6: □ | J6: □ | L6: □
A7: 6 | H7: □ | I7: □ | J7: □ | L7: □
A8: 7 | H8: □ | I8: □ | J8: □ | L8: □
A9: 8 | H9: □ | I9: □ | J9: □ | L9: □
D10: 合計 | E10: =SUM(E2:E9) -> 0 | F10: =SUM(F2:F9) -> 0 | G10: =SUM(G2:G9) -> 0 | L10: {=SUM(G2:G9*IF(L2:L9="■",1,0))} -> 0

Sheet 226_有価証券
A1: No. | B1: 財産の内容 （ゴルフ会員権・株式・出資金等） | C1: 数量 | D1: 証券番号等 | E1: 証券等 ／ 所在場所 | G1: 簿価等（円） | H1: 回収見込額（円） | I1: 取引相場 資料 | J1: 備 考 | K1: 自由財産 拡張申立
A2: 1 | E2: □ | I2: □ | K2: □
A3: 2 | E3: □ | I3: □ | K3: □
A4: 3 | E4: □ | I4: □ | K4: □
A5: 4 | E5: □ | I5: □ | K5: □
A6: 5 | E6: □ | I6: □ | K6: □
A7: 6 | E7: □ | I7: □ | K7: □
A8: 7 | E8: □ | I8: □ | K8: □
A9: 8 | E9: □ | I9: □ | K9: □
E10: 合計 | G10: =SUM(G2:G9) -> 0 | H10: =SUM(H2:H9) -> 0 | K10: {=SUM(H2:H9*IF(K2:K9="■",1,0))} -> 0

Sheet 227_手形・小切手
A1: No. | B1: 振出人の氏名 又は会社名 | C1: 〒 | D1: 住 所 | E1: TEL FAX | F1: 手形小切手番号 | G1: 裏書人 | H1: 支払期日 | I1: 額面（円） | J1: 回収見込額（円） | K1: 備考 | L1: 自由財産 拡張申立
A2: 1 | L2: □
A3: 2 | L3: □
A4: 3 | L4: □
A5: 4 | L5: □
A6: 5 | L6: □
A7: 6 | L7: □
A8: 7 | L8: □
A9: 8 | L9: □
H10: 合計 | I10: =SUM(I2:I9) -> 0 | J10: =SUM(J2:J9) -> 0 | L10: {=SUM(J2:J9*IF(L2:L9="■",1,0))} -> 0

Sheet 228_売掛金
A1: No. | B1: 債務者の氏名 又は会社名 | C1: 〒 | D1: 住 所 | E1: TEL FAX | F1: 金 額（円） | G1: 回収見込額（円） | H1: 契約書等 | I1: 備考 | J1: 自由財産 拡張申立
A2: 1 | H2: □ | J2: □
A3: 2 | H3: □ | J3: □
A4: 3 | H4: □ | J4: □
A5: 4 | H5: □ | J5: □
A6: 5 | H6: □ | J6: □
A7: 6 | H7: □ | J7: □
A8: 7 | H8: □ | J8: □
A9: 8 | H9: □ | J9: □
E10: 合計 | F10: =SUM(F2:F9) -> 0 | G10: =SUM(G2:G9) -> 0 | J10: {=SUM(G2:G9*IF(J2:J9="■",1,0))} -> 0

Sheet 229_貸付金
A1: No. | B1: 債務者の氏名 又は会社名 | C1: 〒 | D1: 住 所 | E1: TEL FAX | F1: 金 額（円） | G1: 回収見込額（円） | H1: 契約書等 | I1: 備考 | J1: 自由財産 拡張申立
A2: 1 | H2: □ | J2: □
A3: 2 | H3: □ | J3: □
A4: 3 | H4: □ | J4: □
A5: 4 | H5: □ | J5: □
A6: 5 | H6: □ | J6: □
A7: 6 | H7: □ | J7: □
A8: 7 | H8: □ | J8: □
A9: 8 | H9: □ | J9: □
E10: 合計 | F10: =SUM(F2:F9) -> 0 | G10: =SUM(G2:G9) -> 0 | J10: {=SUM(G2:G9*IF(J2:J9="■",1,0))} -> 0

Sheet 230_在庫商品
A1: No. | B1: 品名 | C1: 個数 | D1: 所在場所 | E1: 簿価等（円） | F1: 回収見込額（円） | G1: 備考 | H1: 自由財産 拡張申立
A2: 1 | H2: □
A3: 2 | H3: □
A4: 3 | H4: □
A5: 4 | H5: □
A6: 5 | H6: □
A7: 6 | H7: □
A8: 7 | H8: □
A9: 8 | H9: □
D10: 合計 | E10: =SUM(E2:E9) -> 0 | F10: =SUM(F2:F9) -> 0 | H10: {=SUM(F2:F9*IF(H2:H9="■",1,0))} -> 0

Sheet 231_機械・工具類
A1: No. | B1: 名称 | C1: 個数 | D1: 所在場所 | E1: 簿価等（円） | F1: 回収見込額（円） | G1: 備 考 | H1: 自由財産 拡張申立
A2: 1 | H2: □
A3: 2 | H3: □
A4: 3 | H4: □
A5: 4 | H5: □
A6: 5 | H6: □
A7: 6 | H7: □
A8: 7 | H8: □
A9: 8 | H9: □
D10: 合計 | E10: =SUM(E2:E9) -> 0 | F10: =SUM(F2:F9) -> 0 | H10: {=SUM(F2:F9*IF(H2:H9="■",1,0))} -> 0

Sheet 232_什器備品
A1: No. | B1: 品名 | C1: 個数 | D1: 所在場所 | E1: 簿価等（円） | F1: 回収見込額（円） | G1: 備 考 | H1: 自由財産 拡張申立
A2: 1 | H2: □
A3: 2 | H3: □
A4: 3 | H4: □
A5: 4 | H5: □
A6: 5 | H6: □
A7: 6 | H7: □
A8: 7 | H8: □
A9: 8 | H9: □
D10: 合計 | E10: =SUM(E2:E9) -> 0 | F10: =SUM(F2:F9) -> 0 | H10: {=SUM(F2:F9*IF(H2:H9="■",1,0))} -> 0

Sheet 233_その他
A1: No. | B1: 財産の種類・内容 | C1: 数量 | D1: 所在場所 | E1: 簿価等（円） | F1: 回収見込額（円） | G1: 備 考 | H1: 自由財産 拡張申立
A2: 1 | H2: □
A3: 2 | H3: □
A4: 3 | H4: □
A5: 4 | H5: □
A6: 5 | H6: □
A7: 6 | H7: □
A8: 7 | H8: □
A9: 8 | H9: □
D10: 合計 | E10: =SUM(E2:E9) -> 0 | F10: =SUM(F2:F9) -> 0 | H10: {=SUM(F2:F9*IF(H2:H9="■",1,0))} -> 0

Sheet 234_処分済財産
A1: ※ | B1: 決算書が存在する事業者については、最終の決算書に記載されており、かつ申立書別紙財産目録に記載のない財産を記載する。
A2: ※ | B2: それ以外の者については、過去２年以内に処分した財産で20万円以上の価値のあるものを記載する。
A3: ※ | B3: ただし，①現金，②預貯金，⑩受取手形・小切手，⑪売掛金，⑬在庫商品（原材料）など，通常流動性が高いと思われる資産については記入する必要がありません。 ③保険解約返戻金，④自動車，⑤保証金・敷金，⑧不動産，⑨有価証券，⑫貸付金，⑭機械・工具，⑮什器備品，⑯その他の財産等の資産についてのみ記入してください。
A4: 番号 | B4: 財産の種類・内容 | C4: 架空計上 | D4: 処分 | E4: 処分日 | F4: 処分価格(円） | G4: 処分代金の使途 又は 財産目録非掲載の理由 | H4: 決算書 記載
A5: 1 | C5: □ | D5: □ | H5: □
A6: 2 | C6: □ | D6: □ | H6: □
A7: 3 | C7: □ | D7: □ | H7: □
A8: 4 | C8: □ | D8: □ | H8: □
A9: 5 | C9: □ | D9: □ | H9: □
A10: 6 | C10: □ | D10: □ | H10: □
A11: 7 | C11: □ | D11: □ | H11: □
